kbec_plugin/__init__.py
kbec_plugin/kbec_config.py
kbec_plugin/kbec_plugin.py
kbec_plugin/kbec_plugin_external.py
kbec_plugin-0.4.2.dist-info/LICENSE
kbec_plugin-0.4.2.dist-info/METADATA
kbec_plugin-0.4.2.dist-info/WHEEL
kbec_plugin-0.4.2.dist-info/top_level.txt
kbec_plugin-0.4.2.dist-info/RECORD
